setup.py
wsgi_jwt_session.py
wsgi_jwt_session.egg-info/PKG-INFO
wsgi_jwt_session.egg-info/SOURCES.txt
wsgi_jwt_session.egg-info/dependency_links.txt
wsgi_jwt_session.egg-info/not-zip-safe
wsgi_jwt_session.egg-info/top_level.txt