Metadata-Version: 1.1
Name: wsgi-jwt-session
Version: 0.0.1
Summary: A Python WSGI middleware that provides  sessions via a JSON Web Token-encoded cookie.
Home-page: http://github.com/btubbs/wsgi_jwt_session
Author: Brent Tubbs
Author-email: brent.tubbs@gmail.com
License: UNKNOWN
Platform: UNKNOWN
Classifier: License :: OSI Approved :: BSD License
Classifier: Programming Language :: Python
